1.Lab/registerbank/registerbank.sv
module register_bank #(
    parameter WIDTH = 8
    ) (
        input clk,
        input rst,
        input wr_en,
        input [WIDTH-1:0] in,
        output logic [WIDTH-1:0] out
);

always_ff @(posedge clk or posedge rst) begin
    if (rst) begin
        out <= '0;
    end else if (wr_en) begin
        out <= in;
    end
end

endmodule

1.Lab/memory/memory.sv
module memory #(
    parameter WIDTH = 8
) (
    input clk, memoryWrite, memoryRead,
    input [2*WIDTH-1:0] memoryWriteData,
    input [7:0] memoryAddress,
    output logic[2*WIDTH-1:0] memoryOutData
);

logic [2*WIDTH-1:0] mem [0:7];
logic [2:0] addr;

assign addr = memoryAddress[2:0];

always_ff @(posedge clk) begin
    if (memoryWrite) begin
        mem[addr] <= memoryWriteData;
    end
end

// Synchronous read: register the output on the clock edge to avoid
// combinational-race timing issues and to make the output transitions
// observable at clock boundaries (improves toggle/cycle coverage).
always_ff @(posedge clk) begin
    if (memoryRead) begin
        memoryOutData <= mem[addr];
    end else begin
        memoryOutData <= '0;
    end
end
endmodule

1.Lab/alu.sv
module ALU #(
    parameter WIDTH = 8
) (
    input [WIDTH-1:0] in1, in2,
    input [3:0] op,
    input invalid_data,
    output logic [2*WIDTH-1:0] out,
    output logic zero,
    output logic error
);

always_comb begin 

    case (op)
        4'b0000: out = in1 + in2;
        4'b0001: out = in1 - in2;
        4'b0010: out = in1 * in2;
        4'b0011: begin
            if (in2 == 0) begin
                out = 0;
                error = -1;
            end
            else begin
                out = in1 / in2;
            end
        end
    endcase

    zero = (out == 0);
end

endmodule

3.Lab/module.sv
module control (
    input clk,
    input rst,
    input [6:0] cmd_in,
    input p_error,
    output logic aluin_reg_en,
    output logic datain_reg_en,
    output logic memoryWrite, memoryRead, selmux2,
    output logic cpu_rdy,
    output logic aluout_reg_en,
    output logic nvalid_data,
    output logic[1:0] in_select_a,
    output logic[1:0] in_select_b,
    output logic[3:0] opcode
);

logic [2:0] opcode3;

assign in_select_a = cmd_in[6:5];
assign in_select_b = cmd_in[4:3];
assign opcode3 = cmd_in[2:0];
assign opcode = {1'b0, opcode3};

always_comb begin
    aluin_reg_en = 1'b0;
    datain_reg_en = 1'b0;
    memoryWrite = 1'b0;
    memoryRead = 1'b0;
    selmux2 = 1'b0;
    cpu_rdy = 1'b1;
    aluout_reg_en = 1'b0;
    nvalid_data = p_error;

    if (rst) begin
        aluin_reg_en = 1'b0;
        datain_reg_en = 1'b0;
        memoryWrite = 1'b0;
        memoryRead = 1'b0;
        selmux2 = 1'b0;
        cpu_rdy = 1'b0;
        aluout_reg_en = 1'b0;
        nvalid_data = 1'b1;
    end else begin
        case (opcode3)
            3'b000,
            3'b001,
            3'b010,
            3'b011: begin
                aluin_reg_en = 1'b1;
                datain_reg_en = 1'b1;
                selmux2 = 1'b0;
                aluout_reg_en = 1'b1;
            end
            3'b100,
            3'b111: begin
                aluin_reg_en = 1'b0;
                datain_reg_en = 1'b0;
                aluout_reg_en = 1'b0;
            end
            3'b101: begin
                aluin_reg_en = 1'b1;
                datain_reg_en = 1'b1;
                memoryRead = 1'b1;
                selmux2 = 1'b1;
                aluout_reg_en = 1'b1;
            end
            3'b110: begin
                aluin_reg_en = 1'b1;
                datain_reg_en = 1'b1;
                memoryWrite = 1'b1;
                selmux2 = 1'b0;
                aluout_reg_en = 1'b1;
            end
            default: begin
                aluin_reg_en = 1'b0;
                datain_reg_en = 1'b0;
                memoryWrite = 1'b0;
                memoryRead = 1'b0;
                selmux2 = 1'b0;
                aluout_reg_en = 1'b0;
            end
        endcase
    end

    if (p_error) begin
        cpu_rdy = 1'b0;
        nvalid_data = 1'b1;
    end
end

endmodule

3.Lab/top.sv
module top #(
parameter WIDTH = 8
) (
    input clk,
    input rst,
    input [6:0] cmdin,
    input [WIDTH-1:0] din_1,
    input [WIDTH-1:0] din_2,
    input [WIDTH-1:0] din_3,
    output logic[WIDTH-1:0] dout_low,
    output logic[WIDTH-1:0] dout_high,
    output logic cpu_rdy,
    output logic zero,
    output logic error
);

logic [WIDTH-1:0] mux_a_out;
logic [WIDTH-1:0] mux_b_out;
logic [WIDTH-1:0] reg_a_out;
logic [WIDTH-1:0] reg_b_out;
logic [2*WIDTH-1:0] alu_out;
logic [2*WIDTH-1:0] mem_out;
logic [2*WIDTH-1:0] final_out;
logic [7:0] memory_address;
logic [3:0] alu_opcode;
logic aluin_reg_en;
logic datain_reg_en;
logic memoryWrite;
logic memoryRead;
logic selmux2;
logic aluout_reg_en;
logic nvalid_data;
logic [1:0] in_select_a;
logic [1:0] in_select_b;
logic [3:0] opcode;
logic p_error;
logic alu_error;

assign p_error = 1'b0;
assign alu_opcode = opcode;
assign error = alu_error;

always_comb begin
    case (in_select_a)
        2'b00: mux_a_out = din_1;
        2'b01: mux_a_out = din_2;
        2'b10: mux_a_out = din_3;
        default: mux_a_out = dout_low;
    endcase

    case (in_select_b)
        2'b00: mux_b_out = din_1;
        2'b01: mux_b_out = din_2;
        2'b10: mux_b_out = din_3;
        default: mux_b_out = dout_low;
    endcase
end

generate
    if (WIDTH <= 8) begin
        assign memory_address = { {(8-WIDTH){1'b0}}, reg_a_out };
    end else begin
        assign memory_address = reg_a_out[7:0];
    end
endgenerate

control control_inst (
    .clk(clk),
    .rst(rst),
    .cmd_in(cmdin),
    .p_error(p_error),
    .aluin_reg_en(aluin_reg_en),
    .datain_reg_en(datain_reg_en),
    .memoryWrite(memoryWrite),
    .memoryRead(memoryRead),
    .selmux2(selmux2),
    .cpu_rdy(cpu_rdy),
    .aluout_reg_en(aluout_reg_en),
    .nvalid_data(nvalid_data),
    .in_select_a(in_select_a),
    .in_select_b(in_select_b),
    .opcode(opcode)
);

register_bank #(.WIDTH(WIDTH)) reg_a (
    .clk(clk),
    .rst(rst),
    .wr_en(aluin_reg_en),
    .in(mux_a_out),
    .out(reg_a_out)
);

register_bank #(.WIDTH(WIDTH)) reg_b (
    .clk(clk),
    .rst(rst),
    .wr_en(datain_reg_en),
    .in(mux_b_out),
    .out(reg_b_out)
);

ALU #(.WIDTH(WIDTH)) alu_inst (
    .in1(reg_a_out),
    .in2(reg_b_out),
    .op(alu_opcode),
    .invalid_data(nvalid_data),
    .out(alu_out),
    .zero(zero),
    .error(alu_error)
);

memory #(.WIDTH(WIDTH)) memory_inst (
    .clk(clk),
    .memoryWrite(memoryWrite),
    .memoryRead(memoryRead),
    .memoryWriteData(alu_out),
    .memoryAddress(memory_address),
    .memoryOutData(mem_out)
);

assign final_out = selmux2 ? mem_out : alu_out;

register_bank #(.WIDTH(2*WIDTH)) output_reg (
    .clk(clk),
    .rst(rst),
    .wr_en(aluout_reg_en),
    .in(final_out),
    .out({dout_high, dout_low})
);

endmodule

3.Lab/tb_top.sv
`timescale 1ns/1ps

module tb_top;
parameter WIDTH = 8;

logic CLK;
logic rst;
logic [6:0] cmdin;
logic [WIDTH-1:0] din_1;
logic [WIDTH-1:0] din_2;
logic [WIDTH-1:0] din_3;
logic [WIDTH-1:0] dout_low;
logic [WIDTH-1:0] dout_high;
logic cpu_rdy;
logic zero;
logic error;

initial CLK = 0;
always #5 CLK = ~CLK;

top #(.WIDTH(WIDTH)) uut (
    .clk(CLK),
    .rst(rst),
    .cmdin(cmdin),
    .din_1(din_1),
    .din_2(din_2),
    .din_3(din_3),
    .dout_low(dout_low),
    .dout_high(dout_high),
    .cpu_rdy(cpu_rdy),
    .zero(zero),
    .error(error)
);

initial begin
    $dumpfile("top.vcd");
    $dumpvars(0, tb_top);

    rst = 1;
    cmdin = 7'b0;
    din_1 = '0;
    din_2 = '0;
    din_3 = '0;

    #12;
    rst = 0;

    // Add: A = din_1(3), B = din_2(5), opcode = 000
    din_1 = 8'd3;
    din_2 = 8'd5;
    din_3 = 8'd7;
    cmdin = 7'b0001000; // muxA=00, muxB=01, opcode=000
    @(posedge CLK);
    @(posedge CLK);
    $display("ADD result=%0d zero=%b error=%b cpu_rdy=%b", {dout_high, dout_low}, zero, error, cpu_rdy);

    // Store: address = din_1(3), data = din_3(7), opcode = 110
    cmdin = 7'b0010110; // muxA=00, muxB=10, opcode=110
    @(posedge CLK);
    @(posedge CLK);
    $display("STORE result=%0d zero=%b error=%b", {dout_high, dout_low}, zero, error);

    // Load: address = din_1(3), opcode = 101
    cmdin = 7'b0000101; // muxA=00, muxB=00, opcode=101
    @(posedge CLK);
    @(posedge CLK);
    $display("LOAD result=%0d zero=%b error=%b", {dout_high, dout_low}, zero, error);

    // Div: A = din_1(8), B = din_2(2), opcode = 011
    din_1 = 8'd8;
    din_2 = 8'd2;
    cmdin = 7'b0001011; // muxA=00, muxB=01, opcode=011
    @(posedge CLK);
    @(posedge CLK);
    $display("DIV result=%0d zero=%b error=%b", {dout_high, dout_low}, zero, error);

    // Div by zero: A = din_1(8), B = din_2(0), opcode = 011
    din_1 = 8'd8;
    din_2 = 8'd0;
    cmdin = 7'b0001011;
    @(posedge CLK);
    @(posedge CLK);
    $display("DIV_ZERO result=%0d zero=%b error=%b", {dout_high, dout_low}, zero, error);

    $finish;
end
endmodule

top.vcd
$date
	Wed Jun 24 10:50:08 2026
$end
$version
	Icarus Verilog
$end
$timescale
	1ps
$end
$scope module tb_top $end
$var wire 1 ! zero $end
$var wire 1 " error $end
$var wire 8 # dout_low [7:0] $end
$var wire 8 $ dout_high [7:0] $end
$var wire 1 % cpu_rdy $end
$var parameter 32 & WIDTH $end
$var reg 1 ' CLK $end
$var reg 7 ( cmdin [6:0] $end
$var reg 8 ) din_1 [7:0] $end
$var reg 8 * din_2 [7:0] $end
$var reg 8 + din_3 [7:0] $end
$var reg 1 , rst $end
$scope module uut $end
$var wire 4 - alu_opcode [3:0] $end
$var wire 1 ' clk $end
$var wire 7 . cmdin [6:0] $end
$var wire 8 / din_1 [7:0] $end
$var wire 8 0 din_2 [7:0] $end
$var wire 8 1 din_3 [7:0] $end
$var wire 1 " error $end
$var wire 1 2 p_error $end
$var wire 1 , rst $end
$var wire 1 ! zero $end
$var wire 1 3 selmux2 $end
$var wire 8 4 reg_b_out [7:0] $end
$var wire 8 5 reg_a_out [7:0] $end
$var wire 4 6 opcode [3:0] $end
$var wire 1 7 nvalid_data $end
$var wire 8 8 memory_address [7:0] $end
$var wire 1 9 memoryWrite $end
$var wire 1 : memoryRead $end
$var wire 16 ; mem_out [15:0] $end
$var wire 2 < in_select_b [1:0] $end
$var wire 2 = in_select_a [1:0] $end
$var wire 16 > final_out [15:0] $end
$var wire 8 ? dout_low [7:0] $end
$var wire 8 @ dout_high [7:0] $end
$var wire 1 A datain_reg_en $end
$var wire 1 % cpu_rdy $end
$var wire 1 B aluout_reg_en $end
$var wire 1 C aluin_reg_en $end
$var wire 16 D alu_out [15:0] $end
$var wire 1 E alu_error $end
$var parameter 32 F WIDTH $end
$var reg 8 G mux_a_out [7:0] $end
$var reg 8 H mux_b_out [7:0] $end
$scope begin genblk1 $end
$upscope $end
$scope module alu_inst $end
$var wire 4 I op [3:0] $end
$var wire 1 7 invalid_data $end
$var wire 8 J in2 [7:0] $end
$var wire 8 K in1 [7:0] $end
$var parameter 32 L WIDTH $end
$var reg 1 E error $end
$var reg 16 M out [15:0] $end
$var reg 1 ! zero $end
$upscope $end
$scope module control_inst $end
$var wire 1 ' clk $end
$var wire 7 N cmd_in [6:0] $end
$var wire 1 2 p_error $end
$var wire 1 , rst $end
$var wire 3 O opcode3 [2:0] $end
$var wire 4 P opcode [3:0] $end
$var wire 2 Q in_select_b [1:0] $end
$var wire 2 R in_select_a [1:0] $end
$var reg 1 C aluin_reg_en $end
$var reg 1 B aluout_reg_en $end
$var reg 1 % cpu_rdy $end
$var reg 1 A datain_reg_en $end
$var reg 1 : memoryRead $end
$var reg 1 9 memoryWrite $end
$var reg 1 7 nvalid_data $end
$var reg 1 3 selmux2 $end
$upscope $end
$scope module memory_inst $end
$var wire 1 ' clk $end
$var wire 8 S memoryAddress [7:0] $end
$var wire 1 : memoryRead $end
$var wire 1 9 memoryWrite $end
$var wire 16 T memoryWriteData [15:0] $end
$var wire 3 U addr [2:0] $end
$var parameter 32 V WIDTH $end
$var reg 16 W memoryOutData [15:0] $end
$upscope $end
$scope module output_reg $end
$var wire 1 ' clk $end
$var wire 16 X in [15:0] $end
$var wire 1 , rst $end
$var wire 1 B wr_en $end
$var parameter 64 Y WIDTH $end
$var reg 16 Z out [15:0] $end
$upscope $end
$scope module reg_a $end
$var wire 1 ' clk $end
$var wire 8 [ in [7:0] $end
$var wire 1 , rst $end
$var wire 1 C wr_en $end
$var parameter 32 \ WIDTH $end
$var reg 8 ] out [7:0] $end
$upscope $end
$scope module reg_b $end
$var wire 1 ' clk $end
$var wire 8 ^ in [7:0] $end
$var wire 1 , rst $end
$var wire 1 A wr_en $end
$var parameter 32 _ WIDTH $end
$var reg 8 ` out [7:0] $end
$upscope $end
$upscope $end
$upscope $end
$enddefinitions $end
$comment Show the parameter values. $end
$dumpall
b1000 _
b1000 \
b10000 Y
b1000 V
b1000 L
b1000 F
b1000 &
$end
#0
$dumpvars
b0 `
b0 ^
b0 ]
b0 [
b0 Z
b0 X
b0 W
b0 U
b0 T
b0 S
b0 R
b0 Q
b0 P
b0 O
b0 N
b0 M
b0 K
b0 J
b0 I
b0 H
b0 G
0E
b0 D
0C
0B
0A
b0 @
b0 ?
b0 >
b0 =
b0 <
b0 ;
0:
09
b0 8
17
b0 6
b0 5
b0 4
03
02
b0 1
b0 0
b0 /
b0 .
b0 -
1,
b0 +
b0 *
b0 )
b0 (
0'
0%
b0 $
b0 #
0"
1!
$end
#5000
1'
#10000
0'
#12000
b1 <
b1 Q
b101 H
b101 ^
b11 G
b11 [
1B
1A
1C
07
1%
b1000 (
b1000 .
b1000 N
b111 +
b111 1
b101 *
b101 0
b11 )
b11 /
0,
#15000
b1000 >
b1000 X
b11 U
0!
b1000 D
b1000 M
b1000 T
b11 8
b11 S
b11 5
b11 K
b11 ]
b101 4
b101 J
b101 `
1'
#20000
0'
#25000
b1000 #
b1000 ?
b1000 Z
b101 >
b101 X
b111 H
b111 ^
b101 D
b101 M
b101 T
19
1B
1A
1C
b10 <
b10 Q
b110 -
b110 I
b110 6
b110 P
b110 O
b10110 (
b10110 .
b10110 N
1'
#30000
0'
#35000
b111 >
b111 X
b111 D
b111 M
b111 T
b101 #
b101 ?
b111 4
b111 J
b111 `
b101 Z
1'
#40000
0'
#45000
b111 #
b111 ?
b111 Z
b111 >
b111 X
b111 ;
b111 W
b11 H
b11 ^
13
1:
1B
09
1A
1C
b0 <
b0 Q
b101 -
b101 I
b101 6
b101 P
b101 O
b101 (
b101 .
b101 N
1'
#50000
0'
#55000
b11 D
b11 M
b11 T
b11 4
b11 J
b11 `
1'
#60000
0'
#65000
b1 >
b1 X
b0 ;
b0 W
b1 D
b1 M
b1 T
1B
03
0:
1A
1C
b1 <
b1 Q
b11 -
b11 I
b11 6
b11 P
b11 O
b10 H
b10 ^
b1000 G
b1000 [
b1011 (
b1011 .
b1011 N
b10 *
b10 0
b1000 )
b1000 /
1'
#70000
0'
#75000
b100 >
b100 X
b0 U
b100 D
b100 M
b100 T
b1 #
b1 ?
b1000 8
b1000 S
b1000 5
b1000 K
b1000 ]
b10 4
b10 J
b10 `
b1 Z
1'
#80000
0'
#85000
b100 #
b100 ?
b100 Z
b0 H
b0 ^
b0 *
b0 0
1'
#90000
0'
#95000
b0 >
b0 X
1!
1"
1E
b0 D
b0 M
b0 T
b0 4
b0 J
b0 `
1'
#100000
0'
#105000
b0 #
b0 ?
b0 Z
1'
