1. Lab I/memory.sv
module memory #(
    parameter WIDTH = 8
) (
    input clk, memoryWrite, memoryRead,
    input [2*WIDTH-1:0] memoryWriteData,
    input [7:0] memoryAddress,
    output logic[2*WIDTH-1:0] memoryOutData
);

logic [2*WIDTH-1:0] mem [0:7];

always_ff @( posedge clk ) begin 
    if(memoryWrite) begin
        mem[memoryAddress[2:0]] <= memoryWriteData;
    end 
end

always_comb begin 
    if (memoryRead) begin
        memoryOutData = mem[memoryAddress[2:0]];
    end
    else begin
            memoryOutData = '0;
    end
end
endmodule

2.Lab/tb_memory.sv
`timescale 1ns/1ps

module tb_memory;
parameter WIDTH = 8;

logic CLK, memoryWrite, memoryRead;
logic [2*WIDTH-1:0] memoryWriteData;
logic [7:0] memoryAddress;
logic[2*WIDTH-1:0] memoryOutData;

initial CLK = 0;
always #5 CLK = ~CLK;

memory #(WIDTH) uut(
    .clk(CLK),
    .memoryWrite(memoryWrite),
    .memoryRead(memoryRead),
    .memoryWriteData(memoryWriteData),
    .memoryAddress(memoryAddress),
    .memoryOutData(memoryOutData)
);

initial begin
    $dumpfile("memory.vcd");
    $dumpvars(0, tb_memory);
    
    memoryWrite = 0;
    memoryRead = 0;
    memoryAddress = 0;
    memoryWriteData = 0;

    #10
    memoryWrite = 1;
    memoryRead = 0;
    memoryAddress = 0;
    memoryWriteData = 16'h666F;
    
    @(posedge CLK);
    #1;

    #10
    memoryWrite = 1;
    memoryRead = 0;
    memoryAddress = 1;
    memoryWriteData = 16'h6469;
    
    @(posedge CLK);
    #1;

    #10
    memoryWrite = 1;
    memoryRead = 0;
    memoryAddress = 2;
    memoryWriteData = 16'h7365;
    
    @(posedge CLK);
    #1;

    #10
    memoryWrite = 1;
    memoryRead = 0;
    memoryAddress = 3;
    memoryWriteData = 16'h6775;
    
    @(posedge CLK);
    #1;

    #10
    memoryWrite = 1;
    memoryRead = 0;
    memoryAddress = 4;
    memoryWriteData = 16'h0061;
    
    @(posedge CLK);
    #1;

    memoryWrite = 0;
    memoryRead = 1;
    memoryAddress = 0;
    #1
    $display("memoryOutData=%s memoryAddress=%0d", memoryOutData, memoryAddress);
    
    memoryWrite = 0;
    memoryRead = 1;
    memoryAddress = 1;
    #1
    $display("memoryOutData=%s memoryAddress=%0d", memoryOutData, memoryAddress);
    
    memoryWrite = 0;
    memoryRead = 1;
    memoryAddress = 2;
    #1
    $display("memoryOutData=%s memoryAddress=%0d", memoryOutData, memoryAddress);
    
    memoryWrite = 0;
    memoryRead = 1;
    memoryAddress = 3;
    #1
    $display("memoryOutData=%s memoryAddress=%0d", memoryOutData, memoryAddress);
    
    memoryWrite = 0;
    memoryRead = 1;
    memoryAddress = 4;
    #1
    $display("memoryOutData=%s memoryAddress=%0d", memoryOutData, memoryAddress);
    
    $finish;
end

endmodule

1.Lab/memory.vcd
$date
	Tue Jun 23 12:36:37 2026
$end
$version
	Icarus Verilog
$end
$timescale
	1ps
$end
$scope module tb_memory $end
$var wire 16 ! memoryOutData [15:0] $end
$var parameter 32 " WIDTH $end
$var reg 1 # CLK $end
$var reg 8 $ memoryAddress [7:0] $end
$var reg 1 % memoryRead $end
$var reg 1 & memoryWrite $end
$var reg 16 ' memoryWriteData [15:0] $end
$scope module uut $end
$var wire 1 # clk $end
$var wire 8 ( memoryAddress [7:0] $end
$var wire 1 % memoryRead $end
$var wire 1 & memoryWrite $end
$var wire 16 ) memoryWriteData [15:0] $end
$var parameter 32 * WIDTH $end
$var reg 16 + memoryOutData [15:0] $end
$upscope $end
$upscope $end
$enddefinitions $end
$comment Show the parameter values. $end
$dumpall
b1000 *
b1000 "
$end
#0
$dumpvars
b0 +
b0 )
b0 (
b0 '
0&
0%
b0 $
0#
b0 !
$end
#5000
1#
#10000
0#
b110011001101111 '
b110011001101111 )
1&
#15000
1#
#20000
0#
#25000
1#
#26000
b110010001101001 '
b110010001101001 )
b1 $
b1 (
#30000
0#
#35000
1#
#40000
0#
#45000
1#
#46000
b111001101100101 '
b111001101100101 )
b10 $
b10 (
#50000
0#
#55000
1#
#60000
0#
#65000
1#
#66000
b110011101110101 '
b110011101110101 )
b11 $
b11 (
#70000
0#
#75000
1#
#80000
0#
#85000
1#
#86000
b1100001 '
b1100001 )
b100 $
b100 (
#90000
0#
#95000
1#
#96000
b110011001101111 !
b110011001101111 +
b0 $
b0 (
1%
0&
#97000
b110010001101001 !
b110010001101001 +
b1 $
b1 (
#98000
b111001101100101 !
b111001101100101 +
b10 $
b10 (
#99000
b110011101110101 !
b110011101110101 +
b11 $
b11 (
#100000
b1100001 !
b1100001 +
b100 $
b100 (
0#
