1.Lab/muxregister.sv
module mux4_registered #(
parameter WIDTH= 8
) (
input clk,
input rst,
input wr_en,
input [1:0] sel,
input [WIDTH-1:0] in1, in2, in3, in4,
output logic [WIDTH-1:0] out
);

always_ff @(posedge clk or posedge rst) begin
    if (rst) begin
        out <= '0;
    end else if (wr_en) begin
        case (sel)
            2'b00: out <= in1;
            2'b01: out <= in2;
            2'b10: out <= in3;
            2'b11: out <= in4;
        endcase
    end
end

endmodule

2. Lab II/tb_muxregister.sv
`timescale 1ns/1ps

module tb_muxregister;
parameter WIDTH = 8;

logic CLK;
logic rst;
logic wr_en;
logic [1:0] sel;
logic [WIDTH-1:0] in1, in2, in3, in4;
logic [WIDTH-1:0] out;

initial CLK = 0;
always #5 CLK = ~CLK;

mux4_registered #(WIDTH) uut(
    .clk(CLK),
    .rst(rst),
    .wr_en(wr_en),
    .sel(sel),
    .in1(in1),
    .in2(in2),
    .in3(in3),
    .in4(in4),
    .out(out)
);

initial begin
    $dumpfile("muxregister.vcd");
    $dumpvars(0, tb_muxregister);

    rst = 1;
    wr_en = 0;
    in1 = 0;
    in2 = 0;
    in3 = 0;
    in4 = 0;

    #10
    rst = 0;
    in1 = 8'h11;
    in2 = 8'h22;
    in3 = 8'h33;
    in4 = 8'h44;
    wr_en = 1;

    sel = 2'b00; #10;
    $display("select=%b out=%0d", sel, out);

    sel = 2'b01; #10;
    $display("select=%b out=%0d", sel, out);

    sel = 2'b10; #10;
    $display("select=%b out=%0d", sel, out);

    sel = 2'b11; #10;
    $display("select=%b out=%0d", sel, out);
    $finish;
end
endmodule

1. Lab I/muxregister.vcd
$date
	Tue Jun 23 09:01:57 2026
$end
$version
	Icarus Verilog
$end
$timescale
	1ps
$end
$scope module tb_muxregister $end
$var wire 8 ! out [7:0] $end
$var parameter 32 " WIDTH $end
$var reg 1 # CLK $end
$var reg 8 $ in1 [7:0] $end
$var reg 8 % in2 [7:0] $end
$var reg 8 & in3 [7:0] $end
$var reg 8 ' in4 [7:0] $end
$var reg 1 ( rst $end
$var reg 2 ) sel [1:0] $end
$var reg 1 * wr_en $end
$scope module uut $end
$var wire 1 # clk $end
$var wire 8 + in1 [7:0] $end
$var wire 8 , in2 [7:0] $end
$var wire 8 - in3 [7:0] $end
$var wire 8 . in4 [7:0] $end
$var wire 1 ( rst $end
$var wire 2 / sel [1:0] $end
$var wire 1 * wr_en $end
$var parameter 32 0 WIDTH $end
$var reg 8 1 out [7:0] $end
$upscope $end
$upscope $end
$enddefinitions $end
$comment Show the parameter values. $end
$dumpall
b1000 0
b1000 "
$end
#0
$dumpvars
b0 1
bx /
b0 .
b0 -
b0 ,
b0 +
0*
bx )
1(
b0 '
b0 &
b0 %
b0 $
0#
b0 !
$end
#5000
1#
#10000
0#
b0 )
b0 /
1*
b1000100 '
b1000100 .
b110011 &
b110011 -
b100010 %
b100010 ,
b10001 $
b10001 +
0(
#15000
b10001 !
b10001 1
1#
#20000
0#
b1 )
b1 /
#25000
b100010 !
b100010 1
1#
#30000
0#
b10 )
b10 /
#35000
b110011 !
b110011 1
1#
#40000
0#
b11 )
b11 /
#45000
b1000100 !
b1000100 1
1#
